mptrolley/__init__.py
mptrolley/mptrolley_main.py
mptrolley/test_case/test_rich.py
mptrolley-0.0.4.dist-info/LICENSE
mptrolley-0.0.4.dist-info/METADATA
mptrolley-0.0.4.dist-info/WHEEL
mptrolley-0.0.4.dist-info/top_level.txt
mptrolley-0.0.4.dist-info/RECORD
