Metadata-Version: 2.1
Name: mptrolley
Version: 0.0.4
Summary: a simple python module to solve problem in a multiprocessing way.
Author-email: GGN_2015 <premierbob@qq.com>
License: MIT License
Requires-Python: >=3.11
License-File: LICENSE
Requires-Dist: process-wrap-queue
Requires-Dist: rich
